csv_utilite/__init__.py
csv_utilite/conversion.py
csv_utilite/formating.py
csv_utilite/generation.py
csv_utilite/manipulation.py
csv_utilite/reader.py
csv_utilite/validation.py
csv_utilite/writer.py
test/__init__.py
test/test_conversion.py
test/test_formating.py
test/test_generation.py
test/test_manipulation.py
test/test_reader.py
test/test_validation.py
test/test_writer.py
csv_utilite-1.0.1.dist-info/LICENSE
csv_utilite-1.0.1.dist-info/METADATA
csv_utilite-1.0.1.dist-info/WHEEL
csv_utilite-1.0.1.dist-info/top_level.txt
csv_utilite-1.0.1.dist-info/RECORD
