Metadata-Version: 2.1
Name: csv-utilite
Version: 1.0.1
Summary: csv-util is a Python package designed to facilitate working with CSV files in a more convenient and Pythonic manner compared to the built-in csv module.
Author: Khalil Habib Shariff
Author-email: khaleelhabib@outlook.com
Classifier: Development Status :: 3 - Alpha
Classifier: Intended Audience :: Developers
Classifier: Topic :: Software Development :: Build Tools
Classifier: License :: OSI Approved :: MIT License
Classifier: Programming Language :: Python :: 3
Classifier: Programming Language :: Python :: 3.6
Classifier: Programming Language :: Python :: 3.7
Classifier: Programming Language :: Python :: 3.8
Classifier: Programming Language :: Python :: 3.9
License-File: LICENSE
